nuva/__init__.py
nuva/nuva.py
nuva/queries.py
nuva/protobuf/Code_pb2.py
nuva/protobuf/Disease_pb2.py
nuva/protobuf/InjectionMethod_pb2.py
nuva/protobuf/NuvaDatabase_pb2.py
nuva/protobuf/Vaccine_pb2.py
nuva/protobuf/Valence_pb2.py
nuva/protobuf/VersionInfo_pb2.py
nuva/protobuf/__init__.py
nuva_sdk-1.0.0.dist-info/licenses/LICENSE
nuva_sdk-1.0.0.dist-info/METADATA
nuva_sdk-1.0.0.dist-info/WHEEL
nuva_sdk-1.0.0.dist-info/top_level.txt
nuva_sdk-1.0.0.dist-info/RECORD
