Metadata-Version: 2.4
Name: nuva-sdk
Version: 1.0.0
Summary: Unified Vaccine Nomenclature (NUVA) Python SDK
Home-page: https://github.com/nuva/nuva-libs
Author: NUVA Team
Author-email: Syadem <developers@mesvaccins.net>
License-Expression: MIT
Project-URL: Homepage, https://nuva.fr
Project-URL: Documentation, https://nuva.fr/docs
Project-URL: Repository, https://github.com/nuva/nuva-libs
Project-URL: Bug Reports, https://github.com/nuva/nuva-libs/issues
Keywords: vaccine,vaccination,nomenclature,healthcare,immunization
Classifier: Development Status :: 4 - Beta
Classifier: Intended Audience :: Developers
Classifier: Intended Audience :: Healthcare Industry
Classifier: Operating System :: OS Independent
Classifier: Programming Language :: Python :: 3
Classifier: Programming Language :: Python :: 3.7
Classifier: Programming Language :: Python :: 3.8
Classifier: Programming Language :: Python :: 3.9
Classifier: Programming Language :: Python :: 3.10
Classifier: Programming Language :: Python :: 3.11
Classifier: Programming Language :: Python :: 3.12
Classifier: Topic :: Scientific/Engineering :: Medical Science Apps.
Classifier: Topic :: Software Development :: Libraries :: Python Modules
Requires-Python: >=3.7
License-File: LICENSE
Requires-Dist: protobuf>=3.20.0
Requires-Dist: requests>=2.25.0
Dynamic: author
Dynamic: home-page
Dynamic: license-file
Dynamic: requires-python
